{
  "type": "forge:conditional",
  "recipes": [
    {
      "conditions": [
        {
          "type": "allcompressedblock:config_condition",
          "configKey": "General.registerNetherite",
          "expectedValue": true
        }
      ],
      "recipe": {
        "type": "minecraft:crafting_shaped",
        "category": "building",
        "key": {
          "#": {
            "item": "allcompressedblock:compressed_netherite_block_item_59"
          }
        },
        "pattern": [
          "###",
          "###",
          "###"
        ],
        "result": {
          "item": "allcompressedblock:compressed_netherite_block_item_60"
        },
        "show_notification": true
      }
    }
  ]
}